Librarymu/__init__.py
Librarymu/my_class.py
gold33423321-0.0.1.dist-info/LICENSE.TXT
gold33423321-0.0.1.dist-info/METADATA
gold33423321-0.0.1.dist-info/WHEEL
gold33423321-0.0.1.dist-info/top_level.txt
gold33423321-0.0.1.dist-info/RECORD
