Metadata-Version: 2.1
Name: gold33423321
Version: 0.0.1
Summary: UAS
Home-page: https://github.com/SeladaKeju/gold33423321
Author: SeladaKeju
Author-email: <rizqiadit240@gmail.com>
License: MIT
Keywords: UAs,COY
Classifier: Development Status :: 1 - Planning
License-File: LICENSE.TXT
